executiontime/__init__.py
executiontime/py.typed
executiontime-0.4.4.dist-info/LICENSE
executiontime-0.4.4.dist-info/METADATA
executiontime-0.4.4.dist-info/WHEEL
executiontime-0.4.4.dist-info/RECORD
