Metadata-Version: 2.3
Name: executiontime
Version: 0.4.4
Summary: A simple function decorator to display its execution time on the console or in the logs.
License: MIT
Keywords: testing,logging,time,performance,execution
Author: Timokasse
Author-email: Timokasse@users.noreply.github.com
Requires-Python: >=3.9,<4.0
Classifier: Development Status :: 3 - Alpha
Classifier: Environment :: Console
Classifier: Intended Audience :: Developers
Classifier: License :: OSI Approved :: MIT License
Classifier: Natural Language :: French
Classifier: Operating System :: OS Independent
Classifier: Programming Language :: Python :: 3
Classifier: Programming Language :: Python :: 3.9
Classifier: Programming Language :: Python :: 3.10
Classifier: Programming Language :: Python :: 3.11
Classifier: Programming Language :: Python :: 3.12
Classifier: Programming Language :: Python :: 3.13
Classifier: Topic :: Software Development :: Testing
Requires-Dist: colorama (>=0.4.6,<0.5.0)
